yta_programming/__init__.py
yta_programming/attribute_obtainer.py
yta_programming/dataclasses.py
yta_programming/decorators/__init__.py
yta_programming/decorators/requires_dependency.py
yta_programming/decorators/singleton.py
yta_programming/exception.py
yta_programming/metaclasses.py
yta_programming/output.py
yta_programming/parameter_obtainer.py
yta_programming/singleton.py
yta_programming/var.py
yta_programming-0.0.24.dist-info/licenses/LICENSE
yta_programming-0.0.24.dist-info/METADATA
yta_programming-0.0.24.dist-info/WHEEL
yta_programming-0.0.24.dist-info/RECORD
